[
  {
    "id": "swsh12pt5-160",
    "set": "swsh12pt5",
    "name": "Pikachu",
    "supertype": "HPX119",
    "subtypes": ["Basic"],
    "types": ["fire"],
    "number": "160",
    "rarity": "Rare Secret",
    "images": {
      "small": "https://alan0623.github.io/card/images/swsh12pt5/160.png",
      "large": "https://alan0623.github.io/card/images/swsh12pt5/160_hires.png"
    }
  },
  {
    "id": "fantasy-1",
    "set": "fantasy",
    "name": "Charmander",
    "supertype": "HPX119",
    "subtypes": ["Basic"],
    "types": ["fire"],
    "number": "1",
    "rarity": "Common",
    "images": {
      "small": "https://alan0623.github.io/card/images/fantasy/1.png",
      "large": "https://alan0623.github.io/card/images/fantasy/1_hires.png"
    }
  },
  {
    "id": "fantasy-2",
    "set": "fantasy",
    "name": "Charmander",
    "supertype": "HPX119",
    "subtypes": ["Basic"],
    "types": ["fire"],
    "number": "2",
    "rarity": "Common",
    "images": {
      "small": "https://alan0623.github.io/card/images/fantasy/2.png",
      "large": "https://alan0623.github.io/card/images/fantasy/2_hires.png"
    }
  },
  {
    "id": "fantasy-3",
    "set": "fantasy",
    "name": "Charmander",
    "supertype": "HPX119",
    "subtypes": ["Basic"],
    "types": ["fire"],
    "number": "3",
    "rarity": "Common",
    "images": {
      "small": "https://alan0623.github.io/card/images/fantasy/3.png",
      "large": "https://alan0623.github.io/card/images/fantasy/3_hires.png"
    }
  },
  {
    "id": "fantasy-4",
    "set": "fantasy",
    "name": "Charmander",
    "supertype": "HPX119",
    "subtypes": ["Basic"],
    "types": ["fire"],
    "number": "4",
    "rarity": "Common",
    "images": {
      "small": "https://alan0623.github.io/card/images/fantasy/4.png",
      "large": "https://alan0623.github.io/card/images/fantasy/4_hires.png"
    }
  },
  {
    "id": "fantasy-5",
    "set": "fantasy",
    "name": "Charmander",
    "supertype": "HPX119",
    "subtypes": ["Basic"],
    "types": ["fire"],
    "number": "5",
    "rarity": "Common",
    "images": {
      "small": "https://alan0623.github.io/card/images/fantasy/5.png",
      "large": "https://alan0623.github.io/card/images/fantasy/5_hires.png"
    }
  },
  {
    "id": "fantasy-6",
    "set": "fantasy",
    "name": "Charmander",
    "supertype": "HPX119",
    "subtypes": ["Basic"],
    "types": ["fire"],
    "number": "6",
    "rarity": "Common",
    "images": {
      "small": "https://alan0623.github.io/card/images/fantasy/6.png",
      "large": "https://alan0623.github.io/card/images/fantasy/6_hires.png"
    }
  },
  {
    "id": "fantasy-13",
    "set": "fantasy",
    "name": "Charmander",
    "supertype": "HPX119",
    "subtypes": ["Basic"],
    "types": ["fire"],
    "number": "13",
    "rarity": "Common",
    "images": {
      "small": "https://alan0623.github.io/card/images/fantasy/13.png",
      "large": "https://alan0623.github.io/card/images/fantasy/13_hires.png"
    }
  },
  {
    "id": "fantasy-14",
    "set": "fantasy",
    "name": "Charmander",
    "supertype": "HPX119",
    "subtypes": ["Basic"],
    "types": ["fire"],
    "number": "14",
    "rarity": "Common",
    "images": {
      "small": "https://alan0623.github.io/card/images/fantasy/14.png",
      "large": "https://alan0623.github.io/card/images/fantasy/14_hires.png"
    }
  },
  {
    "id": "fantasy-15",
    "set": "fantasy",
    "name": "Charmander",
    "supertype": "HPX119",
    "subtypes": ["Basic"],
    "types": ["fire"],
    "number": "15",
    "rarity": "Common",
    "images": {
      "small": "https://alan0623.github.io/card/images/fantasy/15.png",
      "large": "https://alan0623.github.io/card/images/fantasy/15_hires.png"
    }
  },
  {
    "id": "fantasy-16",
    "set": "fantasy",
    "name": "Charmander",
    "supertype": "HPX119",
    "subtypes": ["Basic"],
    "types": ["fire"],
    "number": "16",
    "rarity": "Common",
    "images": {
      "small": "https://alan0623.github.io/card/images/fantasy/16.png",
      "large": "https://alan0623.github.io/card/images/fantasy/16_hires.png"
    }
  },
  {
    "id": "fantasy-17",
    "set": "fantasy",
    "name": "Charmander",
    "supertype": "HPX119",
    "subtypes": ["Basic"],
    "types": ["fire"],
    "number": "17",
    "rarity": "Common",
    "images": {
      "small": "https://alan0623.github.io/card/images/fantasy/17.png",
      "large": "https://alan0623.github.io/card/images/fantasy/17_hires.png"
    }
  },
  {
    "id": "fantasy-18",
    "set": "fantasy",
    "name": "Charmander",
    "supertype": "HPX119",
    "subtypes": ["Basic"],
    "types": ["fire"],
    "number": "18",
    "rarity": "Common",
    "images": {
      "small": "https://alan0623.github.io/card/images/fantasy/18.png",
      "large": "https://alan0623.github.io/card/images/fantasy/18_hires.png"
    }
  },
  {
    "id": "kids-1",
    "set": "kids",
    "name": "Charmander",
    "supertype": "HPX119",
    "subtypes": ["Basic"],
    "types": ["lightning"],
    "number": "1",
    "rarity": "Common",
    "images": {
      "small": "https://alan0623.github.io/card/images/kids/1.png",
      "large": "https://alan0623.github.io/card/images/kids/1_hires.png"
    }
  },
  {
    "id": "kids-2",
    "set": "kids",
    "name": "Charmander",
    "supertype": "HPX119",
    "subtypes": ["Basic"],
    "types": ["lightning"],
    "number": "2",
    "rarity": "Common",
    "images": {
      "small": "https://alan0623.github.io/card/images/kids/2.png",
      "large": "https://alan0623.github.io/card/images/kids/2_hires.png"
    }
  },
  {
    "id": "kids-3",
    "set": "kids",
    "name": "Charmander",
    "supertype": "HPX119",
    "subtypes": ["Basic"],
    "types": ["lightning"],
    "number": "3",
    "rarity": "Common",
    "images": {
      "small": "https://alan0623.github.io/card/images/kids/3.png",
      "large": "https://alan0623.github.io/card/images/kids/3_hires.png"
    }
  },
  {
    "id": "kids-13",
    "set": "kids",
    "name": "Charmander",
    "supertype": "HPX119",
    "subtypes": ["Basic"],
    "types": ["lightning"],
    "number": "13",
    "rarity": "Common",
    "images": {
      "small": "https://alan0623.github.io/card/images/kids/13.png",
      "large": "https://alan0623.github.io/card/images/kids/13_hires.png"
    }
  },
  {
    "id": "kids-14",
    "set": "kids",
    "name": "Charmander",
    "supertype": "HPX119",
    "subtypes": ["Basic"],
    "types": ["lightning"],
    "number": "14",
    "rarity": "Common",
    "images": {
      "small": "https://alan0623.github.io/card/images/kids/14.png",
      "large": "https://alan0623.github.io/card/images/kids/14_hires.png"
    }
  },
  {
    "id": "kids-15",
    "set": "kids",
    "name": "Charmander",
    "supertype": "HPX119",
    "subtypes": ["Basic"],
    "types": ["lightning"],
    "number": "15",
    "rarity": "Common",
    "images": {
      "small": "https://alan0623.github.io/card/images/kids/15.png",
      "large": "https://alan0623.github.io/card/images/kids/15_hires.png"
    }
  },
  {
    "id": "issues-1",
    "set": "issues",
    "name": "Charmander",
    "supertype": "HPX119",
    "subtypes": ["Basic"],
    "types": ["fire"],
    "number": "1",
    "rarity": "Common",
    "images": {
      "small": "https://alan0623.github.io/card/images/issues/1.png",
      "large": "https://alan0623.github.io/card/images/issues/1_hires.png"
    }
  },
  {
    "id": "issues-2",
    "set": "issues",
    "name": "Charmander",
    "supertype": "HPX119",
    "subtypes": ["Basic"],
    "types": ["fire"],
    "number": "2",
    "rarity": "Common",
    "images": {
      "small": "https://alan0623.github.io/card/images/issues/2.png",
      "large": "https://alan0623.github.io/card/images/issues/2_hires.png"
    }
  },
  {
    "id": "issues-3",
    "set": "issues",
    "name": "Charmander",
    "supertype": "HPX119",
    "subtypes": ["Basic"],
    "types": ["fire"],
    "number": "3",
    "rarity": "Common",
    "images": {
      "small": "https://alan0623.github.io/card/images/issues/3.png",
      "large": "https://alan0623.github.io/card/images/issues/3_hires.png"
    }
  },
  {
    "id": "issues-4",
    "set": "issues",
    "name": "Charmander",
    "supertype": "HPX119",
    "subtypes": ["Basic"],
    "types": ["fire"],
    "number": "4",
    "rarity": "Common",
    "images": {
      "small": "https://alan0623.github.io/card/images/issues/4.png",
      "large": "https://alan0623.github.io/card/images/issues/4_hires.png"
    }
  },
  {
    "id": "issues-5",
    "set": "issues",
    "name": "Charmander",
    "supertype": "HPX119",
    "subtypes": ["Basic"],
    "types": ["fire"],
    "number": "5",
    "rarity": "Common",
    "images": {
      "small": "https://alan0623.github.io/card/images/issues/5.png",
      "large": "https://alan0623.github.io/card/images/issues/5_hires.png"
    }
  },
  {
    "id": "issues-6",
    "set": "issues",
    "name": "Charmander",
    "supertype": "HPX119",
    "subtypes": ["Basic"],
    "types": ["fire"],
    "number": "6",
    "rarity": "Common",
    "images": {
      "small": "https://alan0623.github.io/card/images/issues/6.png",
      "large": "https://alan0623.github.io/card/images/issues/6_hires.png"
    }
  },
  {
    "id": "issues-7",
    "set": "issues",
    "name": "Charmander",
    "supertype": "HPX119",
    "subtypes": ["Basic"],
    "types": ["fire"],
    "number": "7",
    "rarity": "Common",
    "images": {
      "small": "https://alan0623.github.io/card/images/issues/7.png",
      "large": "https://alan0623.github.io/card/images/issues/7_hires.png"
    }
  },
  {
    "id": "issues-8",
    "set": "issues",
    "name": "Charmander",
    "supertype": "HPX119",
    "subtypes": ["Basic"],
    "types": ["fire"],
    "number": "8",
    "rarity": "Common",
    "images": {
      "small": "https://alan0623.github.io/card/images/issues/8.png",
      "large": "https://alan0623.github.io/card/images/issues/8_hires.png"
    }
  },
  {
    "id": "issues-9",
    "set": "issues",
    "name": "Charmander",
    "supertype": "HPX119",
    "subtypes": ["Basic"],
    "types": ["fire"],
    "number": "9",
    "rarity": "Common",
    "images": {
      "small": "https://alan0623.github.io/card/images/issues/9.png",
      "large": "https://alan0623.github.io/card/images/issues/9_hires.png"
    }
  },
  {
    "id": "issues-10",
    "set": "issues",
    "name": "Charmander",
    "supertype": "HPX119",
    "subtypes": ["Basic"],
    "types": ["fire"],
    "number": "10",
    "rarity": "Common",
    "images": {
      "small": "https://alan0623.github.io/card/images/issues/10.png",
      "large": "https://alan0623.github.io/card/images/issues/10_hires.png"
    }
  },
  {
    "id": "issues-11",
    "set": "issues",
    "name": "Charmander",
    "supertype": "HPX119",
    "subtypes": ["Basic"],
    "types": ["fire"],
    "number": "11",
    "rarity": "Common",
    "images": {
      "small": "https://alan0623.github.io/card/images/issues/11.png",
      "large": "https://alan0623.github.io/card/images/issues/11_hires.png"
    }
  },
  {
    "id": "issues-12",
    "set": "issues",
    "name": "Charmander",
    "supertype": "HPX119",
    "subtypes": ["Basic"],
    "types": ["fire"],
    "number": "12",
    "rarity": "Common",
    "images": {
      "small": "https://alan0623.github.io/card/images/issues/12.png",
      "large": "https://alan0623.github.io/card/images/issues/12_hires.png"
    }
  },
  {
    "id": "issues-13",
    "set": "issues",
    "name": "Charmander",
    "supertype": "HPX119",
    "subtypes": ["Basic"],
    "types": ["fire"],
    "number": "13",
    "rarity": "Common",
    "images": {
      "small": "https://alan0623.github.io/card/images/issues/13.png",
      "large": "https://alan0623.github.io/card/images/issues/13_hires.png"
    }
  },
  {
    "id": "issues-14",
    "set": "issues",
    "name": "Charmander",
    "supertype": "HPX119",
    "subtypes": ["Basic"],
    "types": ["fire"],
    "number": "14",
    "rarity": "Common",
    "images": {
      "small": "https://alan0623.github.io/card/images/issues/14.png",
      "large": "https://alan0623.github.io/card/images/issues/14_hires.png"
    }
  },
  {
    "id": "issues-15",
    "set": "issues",
    "name": "Charmander",
    "supertype": "HPX119",
    "subtypes": ["Basic"],
    "types": ["fire"],
    "number": "15",
    "rarity": "Common",
    "images": {
      "small": "https://alan0623.github.io/card/images/issues/15.png",
      "large": "https://alan0623.github.io/card/images/issues/15_hires.png"
    }
  },
  {
    "id": "swshp-SWSH180",
    "set": "swshp",
    "name": "Flareon VMAX",
    "supertype": "HPX119",
    "subtypes": ["VMAX", "Single Strike"],
    "types": ["Fire"],
    "number": "SWSH180",
    "rarity": "Rare Rainbow",
    "images": {
      "small": "https://images.pokemontcg.io/swshp/SWSH180.png",
      "large": "https://images.pokemontcg.io/swshp/SWSH180_hires.png"
    }
  },
  {
    "id": "swshp-SWSH182",
    "set": "swshp",
    "name": "Vaporeon VMAX",
    "supertype": "HPX119",
    "subtypes": ["VMAX", "Rapid Strike"],
    "types": ["fire"],
    "number": "SWSH182",
    "rarity": "Rare Rainbow",
    "images": {
      "small": "https://images.pokemontcg.io/swshp/SWSH182.png",
      "large": "https://images.pokemontcg.io/swshp/SWSH182_hires.png"
    }
  },
  {
    "id": "swshp-SWSH184",
    "set": "swshp",
    "name": "Jolteon VMAX",
    "supertype": "HPX119",
    "subtypes": ["VMAX"],
    "types": ["fire"],
    "number": "SWSH184",
    "rarity": "Rare Rainbow",
    "images": {
      "small": "https://images.pokemontcg.io/swshp/SWSH184.png",
      "large": "https://images.pokemontcg.io/swshp/SWSH184_hires.png"
    }
  },
  {
    "id": "fantasy-16",
    "set": "fantasy",
    "name": "Charmander",
    "supertype": "HPX119",
    "subtypes": ["Basic"],
    "types": ["fire"],
    "number": "16",
    "rarity": "Common",
    "images": {
      "small": "https://alan0623.github.io/card/images/fantasy/16.png",
      "large": "https://alan0623.github.io/card/images/fantasy/16_hires.png"
    }
  },
  {
    "id": "fantasy-17",
    "set": "fantasy",
    "name": "Charmander",
    "supertype": "HPX119",
    "subtypes": ["Basic"],
    "types": ["fire"],
    "number": "17",
    "rarity": "Common",
    "images": {
      "small": "https://alan0623.github.io/card/images/fantasy/17.png",
      "large": "https://alan0623.github.io/card/images/fantasy/17_hires.png"
    }
  },
  {
    "id": "fantasy-18",
    "set": "fantasy",
    "name": "Charmander",
    "supertype": "HPX119",
    "subtypes": ["Basic"],
    "types": ["fire"],
    "number": "18",
    "rarity": "Common",
    "images": {
      "small": "https://alan0623.github.io/card/images/fantasy/18.png",
      "large": "https://alan0623.github.io/card/images/fantasy/18_hires.png"
    }
  },
  {
    "id": "swsh8-270",
    "set": "swsh8",
    "name": "Espeon VMAX",
    "supertype": "HPX119",
    "subtypes": ["VMAX"],
    "types": ["Psychic"],
    "number": "270",
    "rarity": "Rare Rainbow",
    "images": {
      "small": "https://images.pokemontcg.io/swsh8/270.png",
      "large": "https://images.pokemontcg.io/swsh8/270_hires.png",
      "foil": "/img/foils/swsh8/foils/270_foil_etched_swsecret.jpg",
      "mask": "/img/foils/swsh8/masks/270_foil_etched_swsecret.png"
    }
  },
  {
    "id": "swsh8-271",
    "set": "swsh8",
    "name": "Gengar VMAX",
    "supertype": "HPX119",
    "subtypes": ["VMAX", "Single Strike"],
    "types": ["fire"],
    "number": "271",
    "rarity": "Rare Rainbow",
    "images": {
      "small": "https://images.pokemontcg.io/swsh8/271.png",
      "large": "https://images.pokemontcg.io/swsh8/271_hires.png",
      "foil": "/img/foils/swsh8/foils/271_foil_etched_swsecret.jpg",
      "mask": "/img/foils/swsh8/masks/271_foil_etched_swsecret.png"
    }
  },
  {
    "id": "swsh7-215",
    "set": "swsh7",
    "name": "Umbreon VMAX",
    "supertype": "HPX119",
    "subtypes": ["VMAX", "Single Strike"],
    "types": ["fire"],
    "number": "215",
    "rarity": "Rare Rainbow",
    "images": {
      "small": "https://images.pokemontcg.io/swsh7/215.png",
      "large": "https://images.pokemontcg.io/swsh7/215_hires.png",
      "foil": "/img/foils/swsh7/foils/215_foil_etched_swsecret.jpg",
      "mask": "/img/foils/swsh7/masks/215_foil_etched_swsecret.png"
    }
  },
  {
    "id": "pgo-31",
    "set": "pgo",
    "name": "Mewtwo VSTAR",
    "supertype": "HPX119",
    "subtypes": ["VSTAR"],
    "types": ["Psychic"],
    "number": "31",
    "rarity": "Rare Holo VSTAR",
    "images": {
      "small": "https://images.pokemontcg.io/pgo/31.png",
      "large": "https://images.pokemontcg.io/pgo/31_hires.png",
      "foil": "/img/foils/pgo/foils/031_foil_etched_sunpillar.jpg",
      "mask": "/img/foils/pgo/masks/031_foil_etched_sunpillar.png"
    }
  },
  {
    "id": "swshp-SWSH214",
    "set": "swshp",
    "name": "Lucario VSTAR",
    "supertype": "HPX119",
    "subtypes": ["VSTAR"],
    "types": ["Fighting"],
    "number": "SWSH214",
    "rarity": "Rare Holo VSTAR",
    "images": {
      "small": "https://images.pokemontcg.io/swshp/SWSH214.png",
      "large": "https://images.pokemontcg.io/swshp/SWSH214_hires.png",
      "foil": "/img/foils/swshp/foils/214_foil_etched_sunpillar.jpg",
      "mask": "/img/foils/swshp/masks/214_foil_etched_sunpillar.png"
    }
  },
  {
    "id": "swsh9-18",
    "set": "swsh9",
    "name": "Charizard VSTAR",
    "supertype": "HPX119",
    "subtypes": ["VSTAR"],
    "types": ["Fire"],
    "number": "18",
    "rarity": "Rare Holo VSTAR",
    "images": {
      "small": "https://images.pokemontcg.io/swsh9/18.png",
      "large": "https://images.pokemontcg.io/swsh9/18_hires.png",
      "foil": "/img/foils/swsh9/foils/018_foil_etched_sunpillar.jpg",
      "mask": "/img/foils/swsh9/masks/018_foil_etched_sunpillar.png"
    }
  },
  {
    "id": "swsh6-196",
    "set": "swsh6",
    "name": "Peonia",
    "supertype": "Trainer",
    "subtypes": ["Supporter"],
    "number": "196",
    "rarity": "Rare Ultra",
    "images": {
      "small": "https://images.pokemontcg.io/swsh6/196.png",
      "large": "https://images.pokemontcg.io/swsh6/196_hires.png",
      "foil": "/img/foils/swsh6/foils/196_foil_etched_sunpillar.jpg",
      "mask": "/img/foils/swsh6/masks/196_foil_etched_sunpillar.png"
    }
  },
  {
    "id": "swsh9-167",
    "set": "swsh9",
    "name": "Barry",
    "supertype": "Trainer",
    "subtypes": ["Supporter"],
    "number": "167",
    "rarity": "Rare Ultra",
    "images": {
      "small": "https://images.pokemontcg.io/swsh9/167.png",
      "large": "https://images.pokemontcg.io/swsh9/167_hires.png",
      "foil": "/img/foils/swsh9/foils/167_foil_etched_sunpillar.jpg",
      "mask": "/img/foils/swsh9/masks/167_foil_etched_sunpillar.png"
    }
  },
  {
    "id": "swsh1-200",
    "set": "swsh1",
    "name": "Marnie",
    "supertype": "Trainer",
    "subtypes": ["Supporter"],
    "number": "200",
    "rarity": "Rare Ultra",
    "images": {
      "small": "https://images.pokemontcg.io/swsh1/200.png",
      "large": "https://images.pokemontcg.io/swsh1/200_hires.png",
      "foil": "/img/foils/swsh1/foils/200_foil_etched_sunpillar.jpg",
      "mask": "/img/foils/swsh1/masks/200_foil_etched_sunpillar.png"
    }
  },
  {
    "id": "swsh11tg-TG27",
    "set": "swsh11tg",
    "name": "Nessa",
    "supertype": "Trainer",
    "subtypes": ["Supporter"],
    "number": "TG27",
    "rarity": "Rare Ultra",
    "images": {
      "small": "https://images.pokemontcg.io/swsh11tg/TG27.png",
      "large": "https://images.pokemontcg.io/swsh11tg/TG27_hires.png",
      "foil": "/img/foils/swsh11/foils/tg27_foil_etched_sunpillar.jpg",
      "mask": "/img/foils/swsh11/masks/tg27_foil_etched_sunpillar.png"
    }
  },
  {
    "id": "swsh12tg-TG26",
    "set": "swsh12tg",
    "name": "Professor Burnet",
    "supertype": "Trainer",
    "subtypes": ["Supporter"],
    "number": "TG26",
    "rarity": "Rare Ultra",
    "images": {
      "small": "https://images.pokemontcg.io/swsh12tg/TG26.png",
      "large": "https://images.pokemontcg.io/swsh12tg/TG26_hires.png",
      "foil": "/img/foils/swsh12/foils/tg26_foil_etched_sunpillar.jpg",
      "mask": "/img/foils/swsh12/masks/tg26_foil_etched_sunpillar.png"
    }
  },
  {
    "id": "swsh11tg-TG26",
    "set": "swsh11tg",
    "name": "Kabu",
    "supertype": "Trainer",
    "subtypes": ["Supporter"],
    "number": "TG26",
    "rarity": "Rare Ultra",
    "images": {
      "small": "https://images.pokemontcg.io/swsh11tg/TG26.png",
      "large": "https://images.pokemontcg.io/swsh11tg/TG26_hires.png",
      "foil": "/img/foils/swsh11/foils/tg26_foil_etched_sunpillar.jpg",
      "mask": "/img/foils/swsh11/masks/tg26_foil_etched_sunpillar.png"
    }
  },
  {
    "id": "swsh4-188",
    "set": "swsh4",
    "name": "Pikachu VMAX",
    "supertype": "HPX119",
    "subtypes": ["VMAX"],
    "types": ["fire"],
    "number": "188",
    "rarity": "Rare Rainbow",
    "images": {
      "small": "https://images.pokemontcg.io/swsh4/188.png",
      "large": "https://images.pokemontcg.io/swsh4/188_hires.png",
      "foil": "/img/foils/swsh4/foils/188_foil_etched_swsecret.jpg",
      "mask": "/img/foils/swsh4/masks/188_foil_etched_swsecret.png"
    }
  },
  {
    "id": "swsh12-197",
    "set": "swsh12",
    "name": "Alolan Vulpix VSTAR",
    "supertype": "HPX119",
    "subtypes": ["VSTAR"],
    "types": ["fire"],
    "number": "197",
    "rarity": "Rare Rainbow",
    "images": {
      "small": "https://images.pokemontcg.io/swsh12/197.png",
      "large": "https://images.pokemontcg.io/swsh12/197_hires.png",
      "foil": "/img/foils/swsh12/foils/197_foil_etched_swsecret.jpg",
      "mask": "/img/foils/swsh12/masks/197_foil_etched_swsecret.png"
    }
  },
  {
    "id": "swsh10-204",
    "set": "swsh10",
    "name": "Irida",
    "supertype": "Trainer",
    "subtypes": ["Supporter"],
    "number": "204",
    "rarity": "Rare Rainbow",
    "images": {
      "small": "https://images.pokemontcg.io/swsh10/204.png",
      "large": "https://images.pokemontcg.io/swsh10/204_hires.png",
      "foil": "/img/foils/swsh10/foils/204_foil_etched_swsecret.jpg",
      "mask": "/img/foils/swsh10/masks/204_foil_etched_swsecret.png"
    }
  },
  {
    "id": "swsh8-268",
    "set": "swsh8",
    "name": "Mew VMAX",
    "supertype": "HPX119",
    "subtypes": ["VMAX", "Fusion Strike"],
    "types": ["Psychic"],
    "number": "268",
    "rarity": "Rare Rainbow",
    "images": {
      "small": "https://images.pokemontcg.io/swsh8/268.png",
      "large": "https://images.pokemontcg.io/swsh8/268_hires.png",
      "foil": "/img/foils/swsh8/foils/268_foil_etched_swsecret.jpg",
      "mask": "/img/foils/swsh8/masks/268_foil_etched_swsecret.png"
    }
  },
  {
    "id": "swsh9-175",
    "set": "swsh9",
    "name": "Whimsicott VSTAR",
    "supertype": "HPX119",
    "subtypes": ["VSTAR"],
    "types": ["Psychic"],
    "number": "175",
    "rarity": "Rare Rainbow",
    "images": {
      "small": "https://images.pokemontcg.io/swsh9/175.png",
      "large": "https://images.pokemontcg.io/swsh9/175_hires.png",
      "foil": "/img/foils/swsh9/foils/175_foil_etched_swsecret.jpg",
      "mask": "/img/foils/swsh9/masks/175_foil_etched_swsecret.png"
    }
  },
  {
    "id": "swsh12-205",
    "set": "swsh12",
    "name": "Furisode Girl",
    "supertype": "Trainer",
    "subtypes": ["Supporter"],
    "number": "205",
    "rarity": "Rare Rainbow",
    "images": {
      "small": "https://images.pokemontcg.io/swsh12/205.png",
      "large": "https://images.pokemontcg.io/swsh12/205_hires.png",
      "foil": "/img/foils/swsh12/foils/205_foil_etched_swsecret.jpg",
      "mask": "/img/foils/swsh12/masks/205_foil_etched_swsecret.png"
    }
  },
  {
    "id": "swsh2-209",
    "set": "swsh2",
    "name": "Twin Energy",
    "supertype": "Energy",
    "subtypes": ["Special"],
    "number": "209",
    "rarity": "Rare Secret",
    "images": {
      "small": "https://images.pokemontcg.io/swsh2/209.png",
      "large": "https://images.pokemontcg.io/swsh2/209_hires.png",
      "foil": "/img/foils/swsh2/foils/209_foil_etched_swsecret.jpg",
      "mask": "/img/foils/swsh2/masks/209_foil_etched_swsecret.png"
    }
  },
  {
    "id": "swsh9-186",
    "set": "swsh9",
    "name": "Ultra Ball",
    "supertype": "Trainer",
    "subtypes": ["Item"],
    "number": "186",
    "rarity": "Rare Secret",
    "images": {
      "small": "https://images.pokemontcg.io/swsh9/186.png",
      "large": "https://images.pokemontcg.io/swsh9/186_hires.png",
      "foil": "/img/foils/swsh9/foils/186_foil_etched_swsecret.jpg",
      "mask": "/img/foils/swsh9/masks/186_foil_etched_swsecret.png"
    }
  },
  {
    "id": "swsh10-213",
    "set": "swsh10",
    "name": "Path to the Peak",
    "supertype": "Trainer",
    "subtypes": ["Stadium"],
    "number": "213",
    "rarity": "Rare Secret",
    "images": {
      "small": "https://images.pokemontcg.io/swsh10/213.png",
      "large": "https://images.pokemontcg.io/swsh10/213_hires.png",
      "foil": "/img/foils/swsh10/foils/213_foil_etched_swsecret.jpg",
      "mask": "/img/foils/swsh10/masks/213_foil_etched_swsecret.png"
    }
  },
  {
    "id": "swsh8-280",
    "set": "swsh8",
    "name": "Flaaffy",
    "supertype": "HPX119",
    "subtypes": ["Stage 1"],
    "types": ["fire"],
    "number": "280",
    "rarity": "Rare Secret",
    "images": {
      "small": "https://images.pokemontcg.io/swsh8/280.png",
      "large": "https://images.pokemontcg.io/swsh8/280_hires.png",
      "foil": "/img/foils/swsh8/foils/280_foil_etched_swsecret.jpg",
      "mask": "/img/foils/swsh8/masks/280_foil_etched_swsecret.png"
    }
  },
  {
    "id": "swsh9-184",
    "set": "swsh9",
    "name": "Arceus VSTAR",
    "supertype": "HPX119",
    "subtypes": ["VSTAR"],
    "types": ["Colorless"],
    "number": "184",
    "rarity": "Rare Secret",
    "images": {
      "small": "https://images.pokemontcg.io/swsh9/184.png",
      "large": "https://images.pokemontcg.io/swsh9/184_hires.png",
      "foil": "/img/foils/swsh9/foils/184_foil_etched_swsecret.jpg",
      "mask": "/img/foils/swsh9/masks/184_foil_etched_swsecret.png"
    }
  },
  {
    "id": "swsh11tg-TG30",
    "set": "swsh11tg",
    "name": "Mew VMAX",
    "supertype": "HPX119",
    "subtypes": ["VMAX", "Fusion Strike"],
    "types": ["Psychic"],
    "number": "TG30",
    "rarity": "Rare Secret",
    "images": {
      "small": "https://images.pokemontcg.io/swsh11tg/TG30.png",
      "large": "https://images.pokemontcg.io/swsh11tg/TG30_hires.png",
      "foil": "/img/foils/swsh11/foils/tg30_foil_etched_swsecret.jpg",
      "mask": "/img/foils/swsh11/masks/tg30_foil_etched_swsecret.png"
    }
  },
  {
    "id": "swsh9tg-TG16",
    "set": "swsh9tg",
    "name": "Mimikyu V",
    "supertype": "HPX119",
    "subtypes": ["Basic", "V"],
    "types": ["Psychic"],
    "number": "TG16",
    "rarity": "Rare Holo V",
    "images": {
      "small": "https://images.pokemontcg.io/swsh9tg/TG16.png",
      "large": "https://images.pokemontcg.io/swsh9tg/TG16_hires.png",
      "foil": "/img/foils/swsh9/foils/tg16_foil_etched_sunpillar.jpg",
      "mask": "/img/foils/swsh9/masks/tg16_foil_etched_sunpillar.png"
    }
  },
  {
    "id": "swsh9tg-TG18",
    "set": "swsh9tg",
    "name": "Single Strike Urshifu V",
    "supertype": "HPX119",
    "subtypes": ["Basic", "V", "Single Strike"],
    "types": ["Fighting"],
    "number": "TG18",
    "rarity": "Rare Holo V",
    "images": {
      "small": "https://images.pokemontcg.io/swsh9tg/TG18.png",
      "large": "https://images.pokemontcg.io/swsh9tg/TG18_hires.png",
      "foil": "/img/foils/swsh9/foils/tg18_foil_etched_sunpillar.jpg",
      "mask": "/img/foils/swsh9/masks/tg18_foil_etched_sunpillar.png"
    }
  },
  {
    "id": "swsh11tg-TG16",
    "set": "swsh11tg",
    "name": "Pikachu V",
    "supertype": "HPX119",
    "subtypes": ["Basic", "V"],
    "types": ["fire"],
    "number": "TG16",
    "rarity": "Rare Holo V",
    "images": {
      "small": "https://images.pokemontcg.io/swsh11tg/TG16.png",
      "large": "https://images.pokemontcg.io/swsh11tg/TG16_hires.png",
      "foil": "/img/foils/swsh11/foils/tg16_foil_etched_sunpillar.jpg",
      "mask": "/img/foils/swsh11/masks/tg16_foil_etched_sunpillar.png"
    }
  },
  {
    "id": "swsh9tg-TG17",
    "set": "swsh9tg",
    "name": "Mimikyu VMAX",
    "supertype": "HPX119",
    "subtypes": ["VMAX"],
    "types": ["Psychic"],
    "number": "TG17",
    "rarity": "Rare Holo VMAX",
    "images": {
      "small": "https://images.pokemontcg.io/swsh9tg/TG17.png",
      "large": "https://images.pokemontcg.io/swsh9tg/TG17_hires.png",
      "foil": "/img/foils/swsh9/foils/tg17_foil_etched_sunpillar.jpg",
      "mask": "/img/foils/swsh9/masks/tg17_foil_etched_sunpillar.png"
    }
  },
  {
    "id": "swsh9tg-TG19",
    "set": "swsh9tg",
    "name": "Single Strike Urshifu VMAX",
    "supertype": "HPX119",
    "subtypes": ["VMAX", "Single Strike"],
    "types": ["Fighting"],
    "number": "TG19",
    "rarity": "Rare Holo VMAX",
    "images": {
      "small": "https://images.pokemontcg.io/swsh9tg/TG19.png",
      "large": "https://images.pokemontcg.io/swsh9tg/TG19_hires.png",
      "foil": "/img/foils/swsh9/foils/tg19_foil_etched_sunpillar.jpg",
      "mask": "/img/foils/swsh9/masks/tg19_foil_etched_sunpillar.png"
    }
  },
  {
    "id": "swsh11tg-TG17",
    "set": "swsh11tg",
    "name": "Pikachu VMAX",
    "supertype": "HPX119",
    "subtypes": ["VMAX"],
    "types": ["fire"],
    "number": "TG17",
    "rarity": "Rare Holo VMAX",
    "images": {
      "small": "https://images.pokemontcg.io/swsh11tg/TG17.png",
      "large": "https://images.pokemontcg.io/swsh11tg/TG17_hires.png",
      "foil": "/img/foils/swsh11/foils/tg17_foil_etched_sunpillar.jpg",
      "mask": "/img/foils/swsh11/masks/tg17_foil_etched_sunpillar.png"
    }
  },
  {
    "id": "fantasy-7",
    "set": "fantasy",
    "name": "fantasy",
    "supertype": "HPX119",
    "subtypes": ["Basic"],
    "types": ["fire"],
    "number": "7",
    "rarity": "Common"
  },
  {
    "id": "fantasy-8",
    "set": "fantasy",
    "name": "fantasy",
    "supertype": "HPX119",
    "subtypes": ["Basic"],
    "types": ["fire"],
    "number": "8",
    "rarity": "Common"
  },
  {
    "id": "fantasy-9",
    "set": "fantasy",
    "name": "fantasy",
    "supertype": "HPX119",
    "subtypes": ["Basic"],
    "types": ["fire"],
    "number": "9",
    "rarity": "Common"
  },
  {
    "id": "pgo-69",
    "set": "pgo",
    "name": "Squirtle",
    "supertype": "HPX119",
    "subtypes": ["Basic"],
    "types": ["fire"],
    "number": "68",
    "rarity": "Common",
    "images": {
      "small": "https://images.pokemontcg.io/pgo/68.png",
      "large": "https://images.pokemontcg.io/pgo/68_hires.png"
    }
  },
  {
    "id": "swsh1-173",
    "set": "swsh1",
    "name": "Poké Kid",
    "supertype": "Trainer",
    "subtypes": ["Supporter"],
    "number": "173",
    "rarity": "Common",
    "images": {
      "small": "https://images.pokemontcg.io/swsh1/173.png",
      "large": "https://images.pokemontcg.io/swsh1/173_hires.png"
    }
  },
  {
    "id": "swsh9-150",
    "set": "swsh9",
    "name": "Ultra Ball",
    "supertype": "Trainer",
    "subtypes": ["Item"],
    "number": "150",
    "rarity": "Common",
    "images": {
      "small": "https://images.pokemontcg.io/swsh9/150.png",
      "large": "https://images.pokemontcg.io/swsh9/150_hires.png"
    }
  },
  {
    "id": "kids-4",
    "set": "kids",
    "name": "Charmander",
    "supertype": "HPX119",
    "subtypes": ["Basic"],
    "types": ["lightning"],
    "number": "4",
    "rarity": "Common",
    "images": {
      "small": "https://alan0623.github.io/card/images/kids/4.png",
      "large": "https://alan0623.github.io/card/images/kids/4_hires.png"
    }
  },
  {
    "id": "kids-5",
    "set": "kids",
    "name": "Charmander",
    "supertype": "HPX119",
    "subtypes": ["Basic"],
    "types": ["lightning"],
    "number": "5",
    "rarity": "Common",
    "images": {
      "small": "https://alan0623.github.io/card/images/kids/5.png",
      "large": "https://alan0623.github.io/card/images/kids/5_hires.png"
    }
  },
  {
    "id": "kids-6",
    "set": "kids",
    "name": "Charmander",
    "supertype": "HPX119",
    "subtypes": ["Basic"],
    "types": ["lightning"],
    "number": "6",
    "rarity": "Common",
    "images": {
      "small": "https://alan0623.github.io/card/images/kids/6.png",
      "large": "https://alan0623.github.io/card/images/kids/6_hires.png"
    }
  },
  {
    "id": "kids-7",
    "set": "kids",
    "name": "Charmander",
    "supertype": "HPX119",
    "subtypes": ["Basic"],
    "types": ["lightning"],
    "number": "7",
    "rarity": "Common",
    "images": {
      "small": "https://alan0623.github.io/card/images/kids/7.png",
      "large": "https://alan0623.github.io/card/images/kids/7_hires.png"
    }
  },
  {
    "id": "kids-8",
    "set": "kids",
    "name": "Charmander",
    "supertype": "HPX119",
    "subtypes": ["Basic"],
    "types": ["lightning"],
    "number": "8",
    "rarity": "Common",
    "images": {
      "small": "https://alan0623.github.io/card/images/kids/8.png",
      "large": "https://alan0623.github.io/card/images/kids/8_hires.png"
    }
  },
  {
    "id": "kids-9",
    "set": "kids",
    "name": "Charmander",
    "supertype": "HPX119",
    "subtypes": ["Basic"],
    "types": ["lightning"],
    "number": "9",
    "rarity": "Common",
    "images": {
      "small": "https://alan0623.github.io/card/images/kids/9.png",
      "large": "https://alan0623.github.io/card/images/kids/9_hires.png"
    }
  },
  {
    "id": "kids-10",
    "set": "kids",
    "name": "Charmander",
    "supertype": "HPX119",
    "subtypes": ["Basic"],
    "types": ["lightning"],
    "number": "10",
    "rarity": "Common",
    "images": {
      "small": "https://alan0623.github.io/card/images/kids/10.png",
      "large": "https://alan0623.github.io/card/images/kids/10_hires.png"
    }
  },
  {
    "id": "kids-11",
    "set": "kids",
    "name": "Charmander",
    "supertype": "HPX119",
    "subtypes": ["Basic"],
    "types": ["lightning"],
    "number": "11",
    "rarity": "Common",
    "images": {
      "small": "https://alan0623.github.io/card/images/kids/11.png",
      "large": "https://alan0623.github.io/card/images/kids/11_hires.png"
    }
  },
  {
    "id": "kids-12",
    "set": "kids",
    "name": "Charmander",
    "supertype": "HPX119",
    "subtypes": ["Basic"],
    "types": ["lightning"],
    "number": "12",
    "rarity": "Common",
    "images": {
      "small": "https://alan0623.github.io/card/images/kids/12.png",
      "large": "https://alan0623.github.io/card/images/kids/12_hires.png"
    }
  },
  {
    "id": "swsh45sv-SV093",
    "set": "swsh45sv",
    "name": "Minccino",
    "supertype": "HPX119",
    "subtypes": ["Basic"],
    "types": ["Colorless"],
    "number": "SV093",
    "rarity": "Rare Shiny",
    "images": {
      "small": "https://images.pokemontcg.io/swsh45sv/SV093.png",
      "large": "https://images.pokemontcg.io/swsh45sv/SV093_hires.png",
      "foil": "/img/foils/swsh45/foils/sv093_foil_etched_sunpillar.jpg",
      "mask": "/img/foils/swsh45/masks/sv093_foil_etched_sunpillar.png"
    }
  },
  {
    "id": "swsh45sv-SV094",
    "set": "swsh45sv",
    "name": "Cinccino",
    "supertype": "HPX119",
    "subtypes": ["Stage 1"],
    "types": ["Colorless"],
    "number": "SV094",
    "rarity": "Rare Shiny",
    "images": {
      "small": "https://images.pokemontcg.io/swsh45sv/SV094.png",
      "large": "https://images.pokemontcg.io/swsh45sv/SV094_hires.png",
      "foil": "/img/foils/swsh45/foils/sv094_foil_etched_sunpillar.jpg",
      "mask": "/img/foils/swsh45/masks/sv094_foil_etched_sunpillar.png"
    }
  },
  {
    "id": "swsh45sv-SV110",
    "set": "swsh45sv",
    "name": "Lapras V",
    "supertype": "HPX119",
    "subtypes": ["Basic", "V"],
    "types": ["fire"],
    "number": "SV110",
    "rarity": "Rare Holo V",
    "images": {
      "small": "https://images.pokemontcg.io/swsh45sv/SV110.png",
      "large": "https://images.pokemontcg.io/swsh45sv/SV110_hires.png",
      "foil": "/img/foils/swsh45/foils/sv110_foil_etched_sunpillar.jpg",
      "mask": "/img/foils/swsh45/masks/sv110_foil_etched_sunpillar.png"
    }
  },
  {
    "id": "swsh45sv-SV023",
    "set": "swsh45sv",
    "name": "Galarian Darumaka",
    "supertype": "HPX119",
    "subtypes": ["Basic"],
    "types": ["fire"],
    "number": "SV023",
    "rarity": "Rare Shiny",
    "images": {
      "small": "https://images.pokemontcg.io/swsh45sv/SV023.png",
      "large": "https://images.pokemontcg.io/swsh45sv/SV023_hires.png",
      "foil": "/img/foils/swsh45/foils/sv023_foil_etched_sunpillar.jpg",
      "mask": "/img/foils/swsh45/masks/sv023_foil_etched_sunpillar.png"
    }
  },
  {
    "id": "swsh45sv-SV076",
    "set": "swsh45sv",
    "name": "Koffing",
    "supertype": "HPX119",
    "subtypes": ["Basic"],
    "types": ["fire"],
    "number": "SV076",
    "rarity": "Rare Shiny",
    "images": {
      "small": "https://images.pokemontcg.io/swsh45sv/SV076.png",
      "large": "https://images.pokemontcg.io/swsh45sv/SV076_hires.png",
      "foil": "/img/foils/swsh45/foils/sv076_foil_etched_sunpillar.jpg",
      "mask": "/img/foils/swsh45/masks/sv076_foil_etched_sunpillar.png"
    }
  },
  {
    "id": "swsh45sv-SV107",
    "set": "swsh45sv",
    "name": "Charizard VMAX",
    "supertype": "HPX119",
    "subtypes": ["VMAX"],
    "types": ["Fire"],
    "number": "SV107",
    "rarity": "Rare Holo VMAX",
    "images": {
      "small": "https://images.pokemontcg.io/swsh45sv/SV107.png",
      "large": "https://images.pokemontcg.io/swsh45sv/SV107_hires.png",
      "foil": "/img/foils/swsh45/foils/sv107_foil_etched_swsecret.jpg",
      "mask": "/img/foils/swsh45/masks/sv107_foil_etched_swsecret.png"
    }
  }
]
